<?xml version="1.0" encoding="utf-8"?>
<report name="official-embargoes" generated="2024-05-10T23:08:56.595675+02:00">
  <row index="0">
    <cell name="directorate">Directorate</cell>
    <cell name="doi">DOI</cell>
    <cell name="title">Title</cell>
    <cell name="subtitle">Subtitle</cell>
    <cell name="language">Language</cell>
    <cell name="medium">Medium</cell>
    <cell name="availability">Availability</cell>
    <cell name="date of publication">Date of Publication</cell>
    <cell name="embargo date">Embargo Date</cell>
    <cell name="launch date/time">Launch Date/Time</cell>
    <cell name="ilibrary last export date">iLibrary Last Export Date</cell>
    <cell name="freepreview last export date">FreePreview Last Export Date</cell>
    <cell name="oecd.org last export date">OECD.org Last Export Date</cell>
    <cell name="discoveryservice last export date">DiscoveryService Last Export Date</cell>
    <cell name="google last export date">Google Last Export Date</cell>
    <cell name="catalogue type">Catalogue Type</cell>
    <cell name="fti loaded?">FTI Loaded?</cell>
    <cell name="kappa link">Kappa Link</cell>
  </row>
  <row index="1">
    <cell name="directorate">Directorate for Financial and Enterprise Affairs</cell>
    <cell name="doi">10.1787/975b5e78-en</cell>
    <cell name="title">Dividend payments by state-owned enterprises (en)</cell>
    <cell name="subtitle">Policies and practices (en)</cell>
    <cell name="language">English</cell>
    <cell name="medium">PDF</cell>
    <cell name="availability">Published</cell>
    <cell name="date of publication">2024-05-10</cell>
    <cell name="embargo date">2024-05-10T05:00:00Z</cell>
    <cell name="launch date/time"/>
    <cell name="ilibrary last export date">2024-05-07T20:46:05Z</cell>
    <cell name="freepreview last export date"/>
    <cell name="oecd.org last export date">2024-05-10T20:21:54Z</cell>
    <cell name="discoveryservice last export date"/>
    <cell name="google last export date"/>
    <cell name="catalogue type">Paper</cell>
    <cell name="fti loaded?">✓</cell>
    <cell name="kappa link">http://kappa.oecd.org/v3/metadata/3f4629a5</cell>
  </row>
  <row index="2">
    <cell name="directorate">Directorate for Financial and Enterprise Affairs</cell>
    <cell name="doi">10.1787/c20b27ac-de</cell>
    <cell name="title">Finanzbildung in Deutschland (de)</cell>
    <cell name="subtitle">Finanzielle Resilienz und finanzielles Wohlergehen verbessern (de)</cell>
    <cell name="language">German</cell>
    <cell name="medium">PDF</cell>
    <cell name="availability">Published</cell>
    <cell name="date of publication">2024-05-13</cell>
    <cell name="embargo date">2024-05-13T05:00:00Z</cell>
    <cell name="launch date/time"/>
    <cell name="ilibrary last export date">2024-05-07T20:46:05Z</cell>
    <cell name="freepreview last export date"/>
    <cell name="oecd.org last export date">2024-05-07T20:23:49Z</cell>
    <cell name="discoveryservice last export date"/>
    <cell name="google last export date"/>
    <cell name="catalogue type">Paper</cell>
    <cell name="fti loaded?">✓</cell>
    <cell name="kappa link">http://kappa.oecd.org/v3/metadata/45846b78</cell>
  </row>
  <row index="3">
    <cell name="directorate">Directorate for Financial and Enterprise Affairs</cell>
    <cell name="doi">10.1787/c7a28393-en</cell>
    <cell name="title">Financial literacy in Germany (en)</cell>
    <cell name="subtitle">Supporting financial resilience and well-being (en)</cell>
    <cell name="language">English</cell>
    <cell name="medium">PDF</cell>
    <cell name="availability">Published</cell>
    <cell name="date of publication">2024-05-13</cell>
    <cell name="embargo date">2024-05-13T05:00:00Z</cell>
    <cell name="launch date/time"/>
    <cell name="ilibrary last export date">2024-05-07T20:46:05Z</cell>
    <cell name="freepreview last export date"/>
    <cell name="oecd.org last export date">2024-05-07T20:23:49Z</cell>
    <cell name="discoveryservice last export date"/>
    <cell name="google last export date"/>
    <cell name="catalogue type">Paper</cell>
    <cell name="fti loaded?">✓</cell>
    <cell name="kappa link">http://kappa.oecd.org/v3/metadata/f933a884</cell>
  </row>
  <row index="4">
    <cell name="directorate">Directorate for Science, Technology and Industry</cell>
    <cell name="doi">10.1787/a1689dc5-en</cell>
    <cell name="title">OECD Digital Economy Outlook 2024 (Volume 1) (en)</cell>
    <cell name="subtitle">Embracing the Technology Frontier (en)</cell>
    <cell name="language">English</cell>
    <cell name="medium">PDF</cell>
    <cell name="availability">Published</cell>
    <cell name="date of publication">2024-05-14</cell>
    <cell name="embargo date">2024-05-14T07:00:00Z</cell>
    <cell name="launch date/time"/>
    <cell name="ilibrary last export date">2024-05-07T20:46:05Z</cell>
    <cell name="freepreview last export date"/>
    <cell name="oecd.org last export date">2024-05-07T20:23:49Z</cell>
    <cell name="discoveryservice last export date"/>
    <cell name="google last export date"/>
    <cell name="catalogue type">Stand-alone monograph</cell>
    <cell name="fti loaded?">✓</cell>
    <cell name="kappa link">http://kappa.oecd.org/v3/metadata/33e3e76d</cell>
  </row>
  <row index="5">
    <cell name="directorate">Directorate for Science, Technology and Industry</cell>
    <cell name="doi">10.1787/e34abd55-fr</cell>
    <cell name="title">Perspectives de l’économie numérique de l’OCDE 2024 (Volume 1) (fr)</cell>
    <cell name="subtitle">Cap sur la frontière technologique (fr)</cell>
    <cell name="language">French</cell>
    <cell name="medium">PDF</cell>
    <cell name="availability">Not yet available</cell>
    <cell name="date of publication">2024-05-14</cell>
    <cell name="embargo date">2024-05-14T07:00:00Z</cell>
    <cell name="launch date/time"/>
    <cell name="ilibrary last export date"/>
    <cell name="freepreview last export date"/>
    <cell name="oecd.org last export date"/>
    <cell name="discoveryservice last export date"/>
    <cell name="google last export date"/>
    <cell name="catalogue type">Stand-alone monograph</cell>
    <cell name="fti loaded?"/>
    <cell name="kappa link">http://kappa.oecd.org/v3/metadata/8f5c1ab2</cell>
  </row>
  <row index="6">
    <cell name="directorate">Directorate for Science, Technology and Industry</cell>
    <cell name="doi">10.1787/e34abd55-fr</cell>
    <cell name="title">Perspectives de l’économie numérique de l’OCDE 2024 (Volume 1) (fr)</cell>
    <cell name="subtitle">Cap sur la frontière technologique (fr)</cell>
    <cell name="language">French</cell>
    <cell name="medium">Paperback</cell>
    <cell name="availability">Not yet available</cell>
    <cell name="date of publication">2024-05-14</cell>
    <cell name="embargo date">2024-05-14T10:00:00Z</cell>
    <cell name="launch date/time"/>
    <cell name="ilibrary last export date"/>
    <cell name="freepreview last export date"/>
    <cell name="oecd.org last export date"/>
    <cell name="discoveryservice last export date"/>
    <cell name="google last export date"/>
    <cell name="catalogue type">Stand-alone monograph</cell>
    <cell name="fti loaded?"/>
    <cell name="kappa link">http://kappa.oecd.org/v3/metadata/0bddedf8</cell>
  </row>
  <row index="7">
    <cell name="directorate">Directorate for Education and Skills</cell>
    <cell name="doi">10.1787/8f80ce38-en</cell>
    <cell name="title">What Does Child Empowerment Mean Today? (en)</cell>
    <cell name="subtitle">Implications for Education and Well-being (en)</cell>
    <cell name="language">English</cell>
    <cell name="medium">Paperback</cell>
    <cell name="availability">Not yet available</cell>
    <cell name="date of publication">2024-05-15</cell>
    <cell name="embargo date">2024-05-15T12:00:00Z</cell>
    <cell name="launch date/time"/>
    <cell name="ilibrary last export date"/>
    <cell name="freepreview last export date"/>
    <cell name="oecd.org last export date"/>
    <cell name="discoveryservice last export date"/>
    <cell name="google last export date"/>
    <cell name="catalogue type">Book</cell>
    <cell name="fti loaded?"/>
    <cell name="kappa link">http://kappa.oecd.org/v3/metadata/794b7fe3</cell>
  </row>
  <row index="8">
    <cell name="directorate">Directorate for Education and Skills</cell>
    <cell name="doi">10.1787/8f80ce38-en</cell>
    <cell name="title">What Does Child Empowerment Mean Today? (en)</cell>
    <cell name="subtitle">Implications for Education and Well-being (en)</cell>
    <cell name="language">English</cell>
    <cell name="medium">PDF</cell>
    <cell name="availability">Not yet available</cell>
    <cell name="date of publication">2024-05-15</cell>
    <cell name="embargo date">2024-05-15T12:00:00Z</cell>
    <cell name="launch date/time"/>
    <cell name="ilibrary last export date"/>
    <cell name="freepreview last export date"/>
    <cell name="oecd.org last export date"/>
    <cell name="discoveryservice last export date"/>
    <cell name="google last export date"/>
    <cell name="catalogue type">Book</cell>
    <cell name="fti loaded?"/>
    <cell name="kappa link">http://kappa.oecd.org/v3/metadata/8845466a</cell>
  </row>
  <row index="9">
    <cell name="directorate">Directorate for Public Governance</cell>
    <cell name="doi">10.1787/e359bcfc-en</cell>
    <cell name="title">Tackling Violence Against Women in the Middle East and North Africa (en)</cell>
    <cell name="subtitle">Governance and Victim/Survivor-Centred Approaches (en)</cell>
    <cell name="language">English</cell>
    <cell name="medium">PDF</cell>
    <cell name="availability">Not yet available</cell>
    <cell name="date of publication">2024-05-17</cell>
    <cell name="embargo date">2024-05-17T05:00:00Z</cell>
    <cell name="launch date/time"/>
    <cell name="ilibrary last export date"/>
    <cell name="freepreview last export date"/>
    <cell name="oecd.org last export date"/>
    <cell name="discoveryservice last export date"/>
    <cell name="google last export date"/>
    <cell name="catalogue type">Stand-alone monograph</cell>
    <cell name="fti loaded?"/>
    <cell name="kappa link">http://kappa.oecd.org/v3/metadata/341dae85</cell>
  </row>
  <row index="10">
    <cell name="directorate">Directorate for Public Governance</cell>
    <cell name="doi">10.1787/2b5b18b8-es</cell>
    <cell name="title">La Regulación del Lobby y de la Influencia en Chile (es)</cell>
    <cell name="subtitle">Recomendaciones para fortalecer la transparencia y la integridad en la toma de decisiones públicas (es)</cell>
    <cell name="language">Spanish</cell>
    <cell name="medium">PDF</cell>
    <cell name="availability">Not yet available</cell>
    <cell name="date of publication">2024-05-17</cell>
    <cell name="embargo date">2024-05-17T12:00:00Z</cell>
    <cell name="launch date/time"/>
    <cell name="ilibrary last export date"/>
    <cell name="freepreview last export date"/>
    <cell name="oecd.org last export date"/>
    <cell name="discoveryservice last export date"/>
    <cell name="google last export date"/>
    <cell name="catalogue type">Book</cell>
    <cell name="fti loaded?"/>
    <cell name="kappa link">http://kappa.oecd.org/v3/metadata/e4ce704f</cell>
  </row>
  <row index="11">
    <cell name="directorate">Directorate for Public Governance</cell>
    <cell name="doi">10.1787/e84a846f-en</cell>
    <cell name="title">The Regulation of Lobbying and Influence in Chile (en)</cell>
    <cell name="subtitle">Recommendations for Strengthening Transparency and Integrity in Decision Making (en)</cell>
    <cell name="language">English</cell>
    <cell name="medium">PDF</cell>
    <cell name="availability">Not yet available</cell>
    <cell name="date of publication">2024-05-17</cell>
    <cell name="embargo date">2024-05-17T12:00:00Z</cell>
    <cell name="launch date/time"/>
    <cell name="ilibrary last export date"/>
    <cell name="freepreview last export date"/>
    <cell name="oecd.org last export date"/>
    <cell name="discoveryservice last export date"/>
    <cell name="google last export date"/>
    <cell name="catalogue type">Book</cell>
    <cell name="fti loaded?"/>
    <cell name="kappa link">http://kappa.oecd.org/v3/metadata/ff8c4b7a</cell>
  </row>
  <row index="12">
    <cell name="directorate">Directorate for Financial and Enterprise Affairs</cell>
    <cell name="doi">10.1787/395c9956-en</cell>
    <cell name="title">Ownership and Governance of State-Owned Enterprises 2024 (en)</cell>
    <cell name="subtitle"/>
    <cell name="language">English</cell>
    <cell name="medium">PDF</cell>
    <cell name="availability">Not yet available</cell>
    <cell name="date of publication">2024-05-23</cell>
    <cell name="embargo date">2024-05-23T09:00:00Z</cell>
    <cell name="launch date/time"/>
    <cell name="ilibrary last export date"/>
    <cell name="freepreview last export date"/>
    <cell name="oecd.org last export date"/>
    <cell name="discoveryservice last export date"/>
    <cell name="google last export date"/>
    <cell name="catalogue type">Stand-alone monograph</cell>
    <cell name="fti loaded?"/>
    <cell name="kappa link">http://kappa.oecd.org/v3/metadata/7c129d23</cell>
  </row>
  <row index="13">
    <cell name="directorate">Directorate for Financial and Enterprise Affairs</cell>
    <cell name="doi">10.1787/395c9956-en</cell>
    <cell name="title">Ownership and Governance of State-Owned Enterprises 2024 (en)</cell>
    <cell name="subtitle"/>
    <cell name="language">English</cell>
    <cell name="medium">Paperback</cell>
    <cell name="availability">Not yet available</cell>
    <cell name="date of publication">2024-05-23</cell>
    <cell name="embargo date">2024-05-23T09:00:00Z</cell>
    <cell name="launch date/time"/>
    <cell name="ilibrary last export date"/>
    <cell name="freepreview last export date"/>
    <cell name="oecd.org last export date"/>
    <cell name="discoveryservice last export date"/>
    <cell name="google last export date"/>
    <cell name="catalogue type">Stand-alone monograph</cell>
    <cell name="fti loaded?"/>
    <cell name="kappa link">http://kappa.oecd.org/v3/metadata/a59375f7</cell>
  </row>
  <row index="14">
    <cell name="directorate">Environment Directorate</cell>
    <cell name="doi">10.1787/d96d644d-fr</cell>
    <cell name="title">Justice environnementale (fr)</cell>
    <cell name="subtitle">Contexte, défis et approches nationales (fr)</cell>
    <cell name="language">French</cell>
    <cell name="medium">PDF</cell>
    <cell name="availability">Not yet available</cell>
    <cell name="date of publication">2024-05-28</cell>
    <cell name="embargo date">2024-05-28T12:00:00Z</cell>
    <cell name="launch date/time"/>
    <cell name="ilibrary last export date"/>
    <cell name="freepreview last export date"/>
    <cell name="oecd.org last export date"/>
    <cell name="discoveryservice last export date"/>
    <cell name="google last export date"/>
    <cell name="catalogue type">Stand-alone monograph</cell>
    <cell name="fti loaded?"/>
    <cell name="kappa link">http://kappa.oecd.org/v3/metadata/0b4b76ad</cell>
  </row>
  <row index="15">
    <cell name="directorate">Environment Directorate</cell>
    <cell name="doi">10.1787/d96d644d-fr</cell>
    <cell name="title">Justice environnementale (fr)</cell>
    <cell name="subtitle">Contexte, défis et approches nationales (fr)</cell>
    <cell name="language">French</cell>
    <cell name="medium">Paperback</cell>
    <cell name="availability">Not yet available</cell>
    <cell name="date of publication">2024-05-28</cell>
    <cell name="embargo date">2024-05-28T12:00:00Z</cell>
    <cell name="launch date/time"/>
    <cell name="ilibrary last export date"/>
    <cell name="freepreview last export date"/>
    <cell name="oecd.org last export date"/>
    <cell name="discoveryservice last export date"/>
    <cell name="google last export date"/>
    <cell name="catalogue type">Stand-alone monograph</cell>
    <cell name="fti loaded?"/>
    <cell name="kappa link">http://kappa.oecd.org/v3/metadata/9b5dad8a</cell>
  </row>
  <row index="16">
    <cell name="directorate">Environment Directorate</cell>
    <cell name="doi">10.1787/57616eb4-en</cell>
    <cell name="title">Environmental Justice (en)</cell>
    <cell name="subtitle">Context, Challenges and National Approaches (en)</cell>
    <cell name="language">English</cell>
    <cell name="medium">Paperback</cell>
    <cell name="availability">Not yet available</cell>
    <cell name="date of publication">2024-05-28</cell>
    <cell name="embargo date">2024-05-28T12:00:00Z</cell>
    <cell name="launch date/time"/>
    <cell name="ilibrary last export date"/>
    <cell name="freepreview last export date"/>
    <cell name="oecd.org last export date"/>
    <cell name="discoveryservice last export date"/>
    <cell name="google last export date"/>
    <cell name="catalogue type">Stand-alone monograph</cell>
    <cell name="fti loaded?"/>
    <cell name="kappa link">http://kappa.oecd.org/v3/metadata/e2e6b2fe</cell>
  </row>
  <row index="17">
    <cell name="directorate">Environment Directorate</cell>
    <cell name="doi">10.1787/57616eb4-en</cell>
    <cell name="title">Environmental Justice (en)</cell>
    <cell name="subtitle">Context, Challenges and National Approaches (en)</cell>
    <cell name="language">English</cell>
    <cell name="medium">PDF</cell>
    <cell name="availability">Not yet available</cell>
    <cell name="date of publication">2024-05-28</cell>
    <cell name="embargo date">2024-05-28T12:00:00Z</cell>
    <cell name="launch date/time"/>
    <cell name="ilibrary last export date"/>
    <cell name="freepreview last export date"/>
    <cell name="oecd.org last export date"/>
    <cell name="discoveryservice last export date"/>
    <cell name="google last export date"/>
    <cell name="catalogue type">Stand-alone monograph</cell>
    <cell name="fti loaded?"/>
    <cell name="kappa link">http://kappa.oecd.org/v3/metadata/4fedf17c</cell>
  </row>
  <row index="18">
    <cell name="directorate">Environment Directorate</cell>
    <cell name="doi">10.1787/19150727-en</cell>
    <cell name="title">Climate Finance Provided and Mobilised by Developed Countries in 2013-2022 (en)</cell>
    <cell name="subtitle"/>
    <cell name="language">English</cell>
    <cell name="medium">PDF</cell>
    <cell name="availability">Not yet available</cell>
    <cell name="date of publication">2024-05-29</cell>
    <cell name="embargo date">2024-05-29T09:00:00Z</cell>
    <cell name="launch date/time"/>
    <cell name="ilibrary last export date"/>
    <cell name="freepreview last export date"/>
    <cell name="oecd.org last export date"/>
    <cell name="discoveryservice last export date"/>
    <cell name="google last export date"/>
    <cell name="catalogue type">Book</cell>
    <cell name="fti loaded?"/>
    <cell name="kappa link">http://kappa.oecd.org/v3/metadata/6ef7ad55</cell>
  </row>
  <row index="19">
    <cell name="directorate">Economics Department</cell>
    <cell name="doi">10.1787/a28c2090-fr</cell>
    <cell name="title">Études économiques de l’OCDE : France 2024 (fr)</cell>
    <cell name="subtitle"/>
    <cell name="language">French</cell>
    <cell name="medium">PDF</cell>
    <cell name="availability">Not yet available</cell>
    <cell name="date of publication">2024-05-31</cell>
    <cell name="embargo date">2024-05-31T09:00:00Z</cell>
    <cell name="launch date/time"/>
    <cell name="ilibrary last export date"/>
    <cell name="freepreview last export date"/>
    <cell name="oecd.org last export date"/>
    <cell name="discoveryservice last export date"/>
    <cell name="google last export date"/>
    <cell name="catalogue type">Economic survey</cell>
    <cell name="fti loaded?"/>
    <cell name="kappa link">http://kappa.oecd.org/v3/metadata/63d6308f</cell>
  </row>
  <row index="20">
    <cell name="directorate">Economics Department</cell>
    <cell name="doi">10.1787/bd96e2ed-en</cell>
    <cell name="title">OECD Economic Surveys: France 2024 (en)</cell>
    <cell name="subtitle"/>
    <cell name="language">English</cell>
    <cell name="medium">PDF</cell>
    <cell name="availability">Not yet available</cell>
    <cell name="date of publication">2024-05-31</cell>
    <cell name="embargo date">2024-05-31T09:00:00Z</cell>
    <cell name="launch date/time"/>
    <cell name="ilibrary last export date"/>
    <cell name="freepreview last export date"/>
    <cell name="oecd.org last export date"/>
    <cell name="discoveryservice last export date"/>
    <cell name="google last export date"/>
    <cell name="catalogue type">Economic survey</cell>
    <cell name="fti loaded?"/>
    <cell name="kappa link">http://kappa.oecd.org/v3/metadata/28ab4949</cell>
  </row>
  <row index="21">
    <cell name="directorate">Directorate for Public Governance</cell>
    <cell name="doi">10.1787/976bf5d2-pt</cell>
    <cell name="title">Impulsionando o desempenho da Agência Nacional de Águas e Saneamento Básico do Brasil (pt)</cell>
    <cell name="subtitle"/>
    <cell name="language">Portuguese</cell>
    <cell name="medium">Paperback</cell>
    <cell name="availability">Not yet available</cell>
    <cell name="date of publication">2024-06-05</cell>
    <cell name="embargo date">2024-06-05T11:00:00Z</cell>
    <cell name="launch date/time"/>
    <cell name="ilibrary last export date"/>
    <cell name="freepreview last export date"/>
    <cell name="oecd.org last export date"/>
    <cell name="discoveryservice last export date"/>
    <cell name="google last export date"/>
    <cell name="catalogue type">Book</cell>
    <cell name="fti loaded?"/>
    <cell name="kappa link">http://kappa.oecd.org/v3/metadata/ac7a1cc8</cell>
  </row>
  <row index="22">
    <cell name="directorate">Directorate for Public Governance</cell>
    <cell name="doi">10.1787/5b7dffa0-en</cell>
    <cell name="title">Driving Performance at Brazil’s National Agency for Water and Basic Sanitation (en)</cell>
    <cell name="subtitle"/>
    <cell name="language">English</cell>
    <cell name="medium">ePub</cell>
    <cell name="availability">Not yet available</cell>
    <cell name="date of publication">2024-06-05</cell>
    <cell name="embargo date">2024-06-05T11:00:00Z</cell>
    <cell name="launch date/time"/>
    <cell name="ilibrary last export date"/>
    <cell name="freepreview last export date"/>
    <cell name="oecd.org last export date"/>
    <cell name="discoveryservice last export date"/>
    <cell name="google last export date"/>
    <cell name="catalogue type">Book</cell>
    <cell name="fti loaded?"/>
    <cell name="kappa link">http://kappa.oecd.org/v3/metadata/f43fa383</cell>
  </row>
  <row index="23">
    <cell name="directorate">Directorate for Public Governance</cell>
    <cell name="doi">10.1787/5b7dffa0-en</cell>
    <cell name="title">Driving Performance at Brazil’s National Agency for Water and Basic Sanitation (en)</cell>
    <cell name="subtitle"/>
    <cell name="language">English</cell>
    <cell name="medium">HTML</cell>
    <cell name="availability">Not yet available</cell>
    <cell name="date of publication">2024-06-05</cell>
    <cell name="embargo date">2024-06-05T11:00:00Z</cell>
    <cell name="launch date/time"/>
    <cell name="ilibrary last export date"/>
    <cell name="freepreview last export date"/>
    <cell name="oecd.org last export date"/>
    <cell name="discoveryservice last export date"/>
    <cell name="google last export date"/>
    <cell name="catalogue type">Book</cell>
    <cell name="fti loaded?"/>
    <cell name="kappa link">http://kappa.oecd.org/v3/metadata/30429927</cell>
  </row>
  <row index="24">
    <cell name="directorate">Directorate for Public Governance</cell>
    <cell name="doi">10.1787/5b7dffa0-en</cell>
    <cell name="title">Driving Performance at Brazil’s National Agency for Water and Basic Sanitation (en)</cell>
    <cell name="subtitle"/>
    <cell name="language">English</cell>
    <cell name="medium">PDF</cell>
    <cell name="availability">Not yet available</cell>
    <cell name="date of publication">2024-06-05</cell>
    <cell name="embargo date">2024-06-05T11:00:00Z</cell>
    <cell name="launch date/time"/>
    <cell name="ilibrary last export date"/>
    <cell name="freepreview last export date"/>
    <cell name="oecd.org last export date"/>
    <cell name="discoveryservice last export date"/>
    <cell name="google last export date"/>
    <cell name="catalogue type">Book</cell>
    <cell name="fti loaded?"/>
    <cell name="kappa link">http://kappa.oecd.org/v3/metadata/6a71ca6a</cell>
  </row>
  <row index="25">
    <cell name="directorate">Directorate for Public Governance</cell>
    <cell name="doi">10.1787/976bf5d2-pt</cell>
    <cell name="title">Impulsionando o desempenho da Agência Nacional de Águas e Saneamento Básico do Brasil (pt)</cell>
    <cell name="subtitle"/>
    <cell name="language">Portuguese</cell>
    <cell name="medium">ePub</cell>
    <cell name="availability">Not yet available</cell>
    <cell name="date of publication">2024-06-05</cell>
    <cell name="embargo date">2024-06-05T11:00:00Z</cell>
    <cell name="launch date/time"/>
    <cell name="ilibrary last export date"/>
    <cell name="freepreview last export date"/>
    <cell name="oecd.org last export date"/>
    <cell name="discoveryservice last export date"/>
    <cell name="google last export date"/>
    <cell name="catalogue type">Book</cell>
    <cell name="fti loaded?"/>
    <cell name="kappa link">http://kappa.oecd.org/v3/metadata/7796bd06</cell>
  </row>
  <row index="26">
    <cell name="directorate">Directorate for Public Governance</cell>
    <cell name="doi">10.1787/5b7dffa0-en</cell>
    <cell name="title">Driving Performance at Brazil’s National Agency for Water and Basic Sanitation (en)</cell>
    <cell name="subtitle"/>
    <cell name="language">English</cell>
    <cell name="medium">Paperback</cell>
    <cell name="availability">Not yet available</cell>
    <cell name="date of publication">2024-06-05</cell>
    <cell name="embargo date">2024-06-05T11:00:00Z</cell>
    <cell name="launch date/time"/>
    <cell name="ilibrary last export date"/>
    <cell name="freepreview last export date"/>
    <cell name="oecd.org last export date"/>
    <cell name="discoveryservice last export date"/>
    <cell name="google last export date"/>
    <cell name="catalogue type">Book</cell>
    <cell name="fti loaded?"/>
    <cell name="kappa link">http://kappa.oecd.org/v3/metadata/5e5c1197</cell>
  </row>
  <row index="27">
    <cell name="directorate">Directorate for Public Governance</cell>
    <cell name="doi">10.1787/976bf5d2-pt</cell>
    <cell name="title">Impulsionando o desempenho da Agência Nacional de Águas e Saneamento Básico do Brasil (pt)</cell>
    <cell name="subtitle"/>
    <cell name="language">Portuguese</cell>
    <cell name="medium">PDF</cell>
    <cell name="availability">Not yet available</cell>
    <cell name="date of publication">2024-06-05</cell>
    <cell name="embargo date">2024-06-05T11:00:00Z</cell>
    <cell name="launch date/time"/>
    <cell name="ilibrary last export date"/>
    <cell name="freepreview last export date"/>
    <cell name="oecd.org last export date"/>
    <cell name="discoveryservice last export date"/>
    <cell name="google last export date"/>
    <cell name="catalogue type">Book</cell>
    <cell name="fti loaded?"/>
    <cell name="kappa link">http://kappa.oecd.org/v3/metadata/2af6d030</cell>
  </row>
  <row index="28">
    <cell name="directorate">Directorate for Public Governance</cell>
    <cell name="doi">10.1787/976bf5d2-pt</cell>
    <cell name="title">Impulsionando o desempenho da Agência Nacional de Águas e Saneamento Básico do Brasil (pt)</cell>
    <cell name="subtitle"/>
    <cell name="language">Portuguese</cell>
    <cell name="medium">HTML</cell>
    <cell name="availability">Not yet available</cell>
    <cell name="date of publication">2024-06-05</cell>
    <cell name="embargo date">2024-06-05T11:00:00Z</cell>
    <cell name="launch date/time"/>
    <cell name="ilibrary last export date"/>
    <cell name="freepreview last export date"/>
    <cell name="oecd.org last export date"/>
    <cell name="discoveryservice last export date"/>
    <cell name="google last export date"/>
    <cell name="catalogue type">Book</cell>
    <cell name="fti loaded?"/>
    <cell name="kappa link">http://kappa.oecd.org/v3/metadata/60c2ab7a</cell>
  </row>
  <row index="29">
    <cell name="directorate">Development Centre</cell>
    <cell name="doi">10.1787/756b6663-en</cell>
    <cell name="title">Multi-dimensional Review of Lao PDR (en)</cell>
    <cell name="subtitle">Financing Sustainable Development (en)</cell>
    <cell name="language">English</cell>
    <cell name="medium">PDF</cell>
    <cell name="availability">Not yet available</cell>
    <cell name="date of publication">2024-06-06</cell>
    <cell name="embargo date">2024-06-06T02:00:00Z</cell>
    <cell name="launch date/time"/>
    <cell name="ilibrary last export date"/>
    <cell name="freepreview last export date"/>
    <cell name="oecd.org last export date"/>
    <cell name="discoveryservice last export date"/>
    <cell name="google last export date"/>
    <cell name="catalogue type">Book</cell>
    <cell name="fti loaded?"/>
    <cell name="kappa link">http://kappa.oecd.org/v3/metadata/921515af</cell>
  </row>
  <row index="30">
    <cell name="directorate">Development Centre</cell>
    <cell name="doi">10.1787/756b6663-en</cell>
    <cell name="title">Multi-dimensional Review of Lao PDR (en)</cell>
    <cell name="subtitle">Financing Sustainable Development (en)</cell>
    <cell name="language">English</cell>
    <cell name="medium">Paperback</cell>
    <cell name="availability">Not yet available</cell>
    <cell name="date of publication">2024-06-06</cell>
    <cell name="embargo date">2024-06-06T02:00:00Z</cell>
    <cell name="launch date/time"/>
    <cell name="ilibrary last export date"/>
    <cell name="freepreview last export date"/>
    <cell name="oecd.org last export date"/>
    <cell name="discoveryservice last export date"/>
    <cell name="google last export date"/>
    <cell name="catalogue type">Book</cell>
    <cell name="fti loaded?"/>
    <cell name="kappa link">http://kappa.oecd.org/v3/metadata/dad4a933</cell>
  </row>
  <row index="31">
    <cell name="directorate">Development Centre</cell>
    <cell name="doi">10.1787/a9b71040-en</cell>
    <cell name="title">Start-up Asia (en)</cell>
    <cell name="subtitle">Chasing the Innovation Frontier (en)</cell>
    <cell name="language">English</cell>
    <cell name="medium">PDF</cell>
    <cell name="availability">Not yet available</cell>
    <cell name="date of publication">2024-06-20</cell>
    <cell name="embargo date">2024-06-19T22:00:00Z</cell>
    <cell name="launch date/time"/>
    <cell name="ilibrary last export date"/>
    <cell name="freepreview last export date"/>
    <cell name="oecd.org last export date"/>
    <cell name="discoveryservice last export date"/>
    <cell name="google last export date"/>
    <cell name="catalogue type">Book</cell>
    <cell name="fti loaded?"/>
    <cell name="kappa link">http://kappa.oecd.org/v3/metadata/dee98371</cell>
  </row>
  <row index="32">
    <cell name="directorate">Development Centre</cell>
    <cell name="doi">10.1787/a9b71040-en</cell>
    <cell name="title">Start-up Asia (en)</cell>
    <cell name="subtitle">Chasing the Innovation Frontier (en)</cell>
    <cell name="language">English</cell>
    <cell name="medium">Paperback</cell>
    <cell name="availability">Not yet available</cell>
    <cell name="date of publication">2024-06-20</cell>
    <cell name="embargo date">2024-06-19T22:00:00Z</cell>
    <cell name="launch date/time"/>
    <cell name="ilibrary last export date"/>
    <cell name="freepreview last export date"/>
    <cell name="oecd.org last export date"/>
    <cell name="discoveryservice last export date"/>
    <cell name="google last export date"/>
    <cell name="catalogue type">Book</cell>
    <cell name="fti loaded?"/>
    <cell name="kappa link">http://kappa.oecd.org/v3/metadata/5c7df7e3</cell>
  </row>
  <row index="33">
    <cell name="directorate">Global Relations and Cooperation Directorate</cell>
    <cell name="doi">10.1787/82e0432e-en</cell>
    <cell name="title">Western Balkans Competitiveness Outlook 2024: Bosnia and Herzegovina (en)</cell>
    <cell name="subtitle"/>
    <cell name="language">English</cell>
    <cell name="medium">Paperback</cell>
    <cell name="availability">Not yet available</cell>
    <cell name="date of publication"/>
    <cell name="embargo date">2024-06-26T09:30:00Z</cell>
    <cell name="launch date/time"/>
    <cell name="ilibrary last export date"/>
    <cell name="freepreview last export date"/>
    <cell name="oecd.org last export date"/>
    <cell name="discoveryservice last export date"/>
    <cell name="google last export date"/>
    <cell name="catalogue type">Book</cell>
    <cell name="fti loaded?"/>
    <cell name="kappa link">http://kappa.oecd.org/v3/metadata/ca00e352</cell>
  </row>
  <row index="34">
    <cell name="directorate">Global Relations and Cooperation Directorate</cell>
    <cell name="doi">10.1787/3699c0d5-en</cell>
    <cell name="title">Western Balkans Competitiveness Outlook 2024: Serbia (en)</cell>
    <cell name="subtitle"/>
    <cell name="language">English</cell>
    <cell name="medium">PDF</cell>
    <cell name="availability">Not yet available</cell>
    <cell name="date of publication">2024-06-26</cell>
    <cell name="embargo date">2024-06-26T09:30:00Z</cell>
    <cell name="launch date/time"/>
    <cell name="ilibrary last export date"/>
    <cell name="freepreview last export date"/>
    <cell name="oecd.org last export date"/>
    <cell name="discoveryservice last export date"/>
    <cell name="google last export date"/>
    <cell name="catalogue type">Book</cell>
    <cell name="fti loaded?"/>
    <cell name="kappa link">http://kappa.oecd.org/v3/metadata/2e523a97</cell>
  </row>
  <row index="35">
    <cell name="directorate">Global Relations and Cooperation Directorate</cell>
    <cell name="doi">10.1787/ead1588e-en</cell>
    <cell name="title">Western Balkans Competitiveness Outlook 2024: Montenegro (en)</cell>
    <cell name="subtitle"/>
    <cell name="language">English</cell>
    <cell name="medium">Paperback</cell>
    <cell name="availability">Not yet available</cell>
    <cell name="date of publication"/>
    <cell name="embargo date">2024-06-26T09:30:00Z</cell>
    <cell name="launch date/time"/>
    <cell name="ilibrary last export date"/>
    <cell name="freepreview last export date"/>
    <cell name="oecd.org last export date"/>
    <cell name="discoveryservice last export date"/>
    <cell name="google last export date"/>
    <cell name="catalogue type">Book</cell>
    <cell name="fti loaded?"/>
    <cell name="kappa link">http://kappa.oecd.org/v3/metadata/82a111fb</cell>
  </row>
  <row index="36">
    <cell name="directorate">Global Relations and Cooperation Directorate</cell>
    <cell name="doi">10.1787/170b0e53-en</cell>
    <cell name="title">Western Balkans Competitiveness Outlook 2024: Regional Profile (en)</cell>
    <cell name="subtitle"/>
    <cell name="language">English</cell>
    <cell name="medium">PDF</cell>
    <cell name="availability">Not yet available</cell>
    <cell name="date of publication">2024-06-26</cell>
    <cell name="embargo date">2024-06-26T09:30:00Z</cell>
    <cell name="launch date/time"/>
    <cell name="ilibrary last export date"/>
    <cell name="freepreview last export date"/>
    <cell name="oecd.org last export date"/>
    <cell name="discoveryservice last export date"/>
    <cell name="google last export date"/>
    <cell name="catalogue type">Book</cell>
    <cell name="fti loaded?"/>
    <cell name="kappa link">http://kappa.oecd.org/v3/metadata/3119c262</cell>
  </row>
  <row index="37">
    <cell name="directorate">Global Relations and Cooperation Directorate</cell>
    <cell name="doi">10.1787/541ec4e7-en</cell>
    <cell name="title">Western Balkans Competitiveness Outlook 2024: Albania (en)</cell>
    <cell name="subtitle"/>
    <cell name="language">English</cell>
    <cell name="medium">Paperback</cell>
    <cell name="availability">Not yet available</cell>
    <cell name="date of publication"/>
    <cell name="embargo date">2024-06-26T09:30:00Z</cell>
    <cell name="launch date/time"/>
    <cell name="ilibrary last export date"/>
    <cell name="freepreview last export date"/>
    <cell name="oecd.org last export date"/>
    <cell name="discoveryservice last export date"/>
    <cell name="google last export date"/>
    <cell name="catalogue type">Book</cell>
    <cell name="fti loaded?"/>
    <cell name="kappa link">http://kappa.oecd.org/v3/metadata/b2da11d0</cell>
  </row>
  <row index="38">
    <cell name="directorate">Global Relations and Cooperation Directorate</cell>
    <cell name="doi">10.1787/ff74ae0e-en</cell>
    <cell name="title">Western Balkans Competitiveness Outlook 2024: Kosovo (en)</cell>
    <cell name="subtitle"/>
    <cell name="language">English</cell>
    <cell name="medium">PDF</cell>
    <cell name="availability">Not yet available</cell>
    <cell name="date of publication"/>
    <cell name="embargo date">2024-06-26T09:30:00Z</cell>
    <cell name="launch date/time"/>
    <cell name="ilibrary last export date"/>
    <cell name="freepreview last export date"/>
    <cell name="oecd.org last export date"/>
    <cell name="discoveryservice last export date"/>
    <cell name="google last export date"/>
    <cell name="catalogue type">Book</cell>
    <cell name="fti loaded?"/>
    <cell name="kappa link">http://kappa.oecd.org/v3/metadata/748583c7</cell>
  </row>
  <row index="39">
    <cell name="directorate">Global Relations and Cooperation Directorate</cell>
    <cell name="doi">10.1787/ff74ae0e-en</cell>
    <cell name="title">Western Balkans Competitiveness Outlook 2024: Kosovo (en)</cell>
    <cell name="subtitle"/>
    <cell name="language">English</cell>
    <cell name="medium">Paperback</cell>
    <cell name="availability">Not yet available</cell>
    <cell name="date of publication"/>
    <cell name="embargo date">2024-06-26T09:30:00Z</cell>
    <cell name="launch date/time"/>
    <cell name="ilibrary last export date"/>
    <cell name="freepreview last export date"/>
    <cell name="oecd.org last export date"/>
    <cell name="discoveryservice last export date"/>
    <cell name="google last export date"/>
    <cell name="catalogue type">Book</cell>
    <cell name="fti loaded?"/>
    <cell name="kappa link">http://kappa.oecd.org/v3/metadata/ce978234</cell>
  </row>
  <row index="40">
    <cell name="directorate">Global Relations and Cooperation Directorate</cell>
    <cell name="doi">10.1787/541ec4e7-en</cell>
    <cell name="title">Western Balkans Competitiveness Outlook 2024: Albania (en)</cell>
    <cell name="subtitle"/>
    <cell name="language">English</cell>
    <cell name="medium">PDF</cell>
    <cell name="availability">Not yet available</cell>
    <cell name="date of publication"/>
    <cell name="embargo date">2024-06-26T09:30:00Z</cell>
    <cell name="launch date/time"/>
    <cell name="ilibrary last export date"/>
    <cell name="freepreview last export date"/>
    <cell name="oecd.org last export date"/>
    <cell name="discoveryservice last export date"/>
    <cell name="google last export date"/>
    <cell name="catalogue type">Book</cell>
    <cell name="fti loaded?"/>
    <cell name="kappa link">http://kappa.oecd.org/v3/metadata/e3d0490a</cell>
  </row>
  <row index="41">
    <cell name="directorate">Global Relations and Cooperation Directorate</cell>
    <cell name="doi">10.1787/ead1588e-en</cell>
    <cell name="title">Western Balkans Competitiveness Outlook 2024: Montenegro (en)</cell>
    <cell name="subtitle"/>
    <cell name="language">English</cell>
    <cell name="medium">PDF</cell>
    <cell name="availability">Not yet available</cell>
    <cell name="date of publication"/>
    <cell name="embargo date">2024-06-26T09:30:00Z</cell>
    <cell name="launch date/time"/>
    <cell name="ilibrary last export date"/>
    <cell name="freepreview last export date"/>
    <cell name="oecd.org last export date"/>
    <cell name="discoveryservice last export date"/>
    <cell name="google last export date"/>
    <cell name="catalogue type">Book</cell>
    <cell name="fti loaded?"/>
    <cell name="kappa link">http://kappa.oecd.org/v3/metadata/b79e5438</cell>
  </row>
  <row index="42">
    <cell name="directorate">Global Relations and Cooperation Directorate</cell>
    <cell name="doi">10.1787/8207326d-en</cell>
    <cell name="title">Western Balkans Competitiveness Outlook 2024: North Macedonia (en)</cell>
    <cell name="subtitle"/>
    <cell name="language">English</cell>
    <cell name="medium">Paperback</cell>
    <cell name="availability">Not yet available</cell>
    <cell name="date of publication"/>
    <cell name="embargo date">2024-06-26T09:30:00Z</cell>
    <cell name="launch date/time"/>
    <cell name="ilibrary last export date"/>
    <cell name="freepreview last export date"/>
    <cell name="oecd.org last export date"/>
    <cell name="discoveryservice last export date"/>
    <cell name="google last export date"/>
    <cell name="catalogue type">Book</cell>
    <cell name="fti loaded?"/>
    <cell name="kappa link">http://kappa.oecd.org/v3/metadata/b6fedfff</cell>
  </row>
  <row index="43">
    <cell name="directorate">Global Relations and Cooperation Directorate</cell>
    <cell name="doi">10.1787/82e0432e-en</cell>
    <cell name="title">Western Balkans Competitiveness Outlook 2024: Bosnia and Herzegovina (en)</cell>
    <cell name="subtitle"/>
    <cell name="language">English</cell>
    <cell name="medium">PDF</cell>
    <cell name="availability">Not yet available</cell>
    <cell name="date of publication"/>
    <cell name="embargo date">2024-06-26T09:30:00Z</cell>
    <cell name="launch date/time"/>
    <cell name="ilibrary last export date"/>
    <cell name="freepreview last export date"/>
    <cell name="oecd.org last export date"/>
    <cell name="discoveryservice last export date"/>
    <cell name="google last export date"/>
    <cell name="catalogue type">Book</cell>
    <cell name="fti loaded?"/>
    <cell name="kappa link">http://kappa.oecd.org/v3/metadata/7e1a14b3</cell>
  </row>
  <row index="44">
    <cell name="directorate">Global Relations and Cooperation Directorate</cell>
    <cell name="doi">10.1787/170b0e53-en</cell>
    <cell name="title">Western Balkans Competitiveness Outlook 2024: Regional Profile (en)</cell>
    <cell name="subtitle"/>
    <cell name="language">English</cell>
    <cell name="medium">Paperback</cell>
    <cell name="availability">Not yet available</cell>
    <cell name="date of publication">2024-06-26</cell>
    <cell name="embargo date">2024-06-26T09:30:00Z</cell>
    <cell name="launch date/time"/>
    <cell name="ilibrary last export date"/>
    <cell name="freepreview last export date"/>
    <cell name="oecd.org last export date"/>
    <cell name="discoveryservice last export date"/>
    <cell name="google last export date"/>
    <cell name="catalogue type">Book</cell>
    <cell name="fti loaded?"/>
    <cell name="kappa link">http://kappa.oecd.org/v3/metadata/be4a569d</cell>
  </row>
  <row index="45">
    <cell name="directorate">Global Relations and Cooperation Directorate</cell>
    <cell name="doi">10.1787/8207326d-en</cell>
    <cell name="title">Western Balkans Competitiveness Outlook 2024: North Macedonia (en)</cell>
    <cell name="subtitle"/>
    <cell name="language">English</cell>
    <cell name="medium">PDF</cell>
    <cell name="availability">Not yet available</cell>
    <cell name="date of publication"/>
    <cell name="embargo date">2024-06-26T09:30:00Z</cell>
    <cell name="launch date/time"/>
    <cell name="ilibrary last export date"/>
    <cell name="freepreview last export date"/>
    <cell name="oecd.org last export date"/>
    <cell name="discoveryservice last export date"/>
    <cell name="google last export date"/>
    <cell name="catalogue type">Book</cell>
    <cell name="fti loaded?"/>
    <cell name="kappa link">http://kappa.oecd.org/v3/metadata/b58d94f5</cell>
  </row>
  <row index="46">
    <cell name="directorate">Global Relations and Cooperation Directorate</cell>
    <cell name="doi">10.1787/3699c0d5-en</cell>
    <cell name="title">Western Balkans Competitiveness Outlook 2024: Serbia (en)</cell>
    <cell name="subtitle"/>
    <cell name="language">English</cell>
    <cell name="medium">Paperback</cell>
    <cell name="availability">Not yet available</cell>
    <cell name="date of publication">2024-06-26</cell>
    <cell name="embargo date">2024-06-26T09:30:00Z</cell>
    <cell name="launch date/time"/>
    <cell name="ilibrary last export date"/>
    <cell name="freepreview last export date"/>
    <cell name="oecd.org last export date"/>
    <cell name="discoveryservice last export date"/>
    <cell name="google last export date"/>
    <cell name="catalogue type">Book</cell>
    <cell name="fti loaded?"/>
    <cell name="kappa link">http://kappa.oecd.org/v3/metadata/0ea6476d</cell>
  </row>
</report>
