<?xml version="1.0" encoding="utf-8"?>
<report name="official-embargoes" generated="2018-11-15T11:17:33.3577849+01:00" count="52">
  <row index="0">
    <cell name="directorate">Directorate</cell>
    <cell name="doi">DOI</cell>
    <cell name="title">Title</cell>
    <cell name="subtitle">Subtitle</cell>
    <cell name="language">Language</cell>
    <cell name="medium">Medium</cell>
    <cell name="availability">Availability</cell>
    <cell name="date of publication">Date of Publication</cell>
    <cell name="embargo date">Embargo Date</cell>
    <cell name="launch date/time">Launch Date/Time</cell>
    <cell name="ilibrary last export date">iLibrary Last Export Date</cell>
    <cell name="freepreview last export date">FreePreview Last Export Date</cell>
    <cell name="catalogue type">Catalogue Type</cell>
    <cell name="fti loaded?">FTI Loaded?</cell>
  </row>
  <row index="1">
    <cell name="directorate">Directorate for Financial and Enterprise Affairs</cell>
    <cell name="doi">10.1787/9789264306929-en</cell>
    <cell name="title">Financial Incentives and Retirement Savings (en)</cell>
    <cell name="subtitle"/>
    <cell name="language">English</cell>
    <cell name="medium">PDF</cell>
    <cell name="availability">Forthcoming</cell>
    <cell name="date of publication">2018-12-03</cell>
    <cell name="embargo date">2018-12-03T09:00:00Z</cell>
    <cell name="launch date/time">2018-12-03T09:00:00Z</cell>
    <cell name="ilibrary last export date">2018-11-09T06:38:47.273Z</cell>
    <cell name="freepreview last export date"/>
    <cell name="catalogue type">Stand-alone monograph</cell>
    <cell name="fti loaded?"/>
  </row>
  <row index="2">
    <cell name="directorate">Directorate for Financial and Enterprise Affairs</cell>
    <cell name="doi">10.1787/9789264306929-en</cell>
    <cell name="title">Financial Incentives and Retirement Savings (en)</cell>
    <cell name="subtitle"/>
    <cell name="language">English</cell>
    <cell name="medium">Paperback</cell>
    <cell name="availability">Forthcoming</cell>
    <cell name="date of publication">2018-12-03</cell>
    <cell name="embargo date">2018-12-03T09:00:00Z</cell>
    <cell name="launch date/time">2018-12-03T09:00:00Z</cell>
    <cell name="ilibrary last export date"/>
    <cell name="freepreview last export date"/>
    <cell name="catalogue type">Stand-alone monograph</cell>
    <cell name="fti loaded?"/>
  </row>
  <row index="3">
    <cell name="directorate">Directorate for Employment, Labour and Social Affairs, Directorate for Financial and Enterprise Affairs</cell>
    <cell name="doi">10.1787/pens_outlook-2018-en</cell>
    <cell name="title">OECD Pensions Outlook 2018 (en)</cell>
    <cell name="subtitle"/>
    <cell name="language">English</cell>
    <cell name="medium">PDF</cell>
    <cell name="availability">Forthcoming</cell>
    <cell name="date of publication">2018-12-03</cell>
    <cell name="embargo date">2018-12-03T09:00:00Z</cell>
    <cell name="launch date/time">2018-12-03T09:00:00Z</cell>
    <cell name="ilibrary last export date">2018-11-10T05:13:45.987Z</cell>
    <cell name="freepreview last export date"/>
    <cell name="catalogue type">Book</cell>
    <cell name="fti loaded?"/>
  </row>
  <row index="4">
    <cell name="directorate">Directorate for Employment, Labour and Social Affairs, Directorate for Financial and Enterprise Affairs</cell>
    <cell name="doi">10.1787/pens_outlook-2018-en</cell>
    <cell name="title">OECD Pensions Outlook 2018 (en)</cell>
    <cell name="subtitle"/>
    <cell name="language">English</cell>
    <cell name="medium">Paperback</cell>
    <cell name="availability">Forthcoming</cell>
    <cell name="date of publication">2018-12-03</cell>
    <cell name="embargo date">2018-12-03T09:00:00Z</cell>
    <cell name="launch date/time">2018-12-03T09:00:00Z</cell>
    <cell name="ilibrary last export date"/>
    <cell name="freepreview last export date"/>
    <cell name="catalogue type">Book</cell>
    <cell name="fti loaded?"/>
  </row>
  <row index="5">
    <cell name="directorate">Centre for Entrepreneurship, SMEs and Local Development</cell>
    <cell name="doi">10.1787/9789264301450-en</cell>
    <cell name="title">SME and Entrepreneurship Policy in Kazakhstan 2018 (en)</cell>
    <cell name="subtitle"/>
    <cell name="language">English</cell>
    <cell name="medium">Paperback</cell>
    <cell name="availability">Not yet available</cell>
    <cell name="date of publication">2018-11-22</cell>
    <cell name="embargo date">2018-11-30T10:00:00Z</cell>
    <cell name="launch date/time">2018-12-04T23:01:00Z</cell>
    <cell name="ilibrary last export date"/>
    <cell name="freepreview last export date"/>
    <cell name="catalogue type">Book</cell>
    <cell name="fti loaded?"/>
  </row>
  <row index="6">
    <cell name="directorate">Centre for Entrepreneurship, SMEs and Local Development</cell>
    <cell name="doi">10.1787/9789264301450-en</cell>
    <cell name="title">SME and Entrepreneurship Policy in Kazakhstan 2018 (en)</cell>
    <cell name="subtitle"/>
    <cell name="language">English</cell>
    <cell name="medium">PDF</cell>
    <cell name="availability">Forthcoming</cell>
    <cell name="date of publication">2018-11-22</cell>
    <cell name="embargo date">2018-11-30T10:00:00Z</cell>
    <cell name="launch date/time">2018-11-30T10:00:00Z</cell>
    <cell name="ilibrary last export date">2018-11-14T05:31:08.533Z</cell>
    <cell name="freepreview last export date"/>
    <cell name="catalogue type">Book</cell>
    <cell name="fti loaded?"/>
  </row>
  <row index="7">
    <cell name="directorate">Centre for Tax Policy and Administration</cell>
    <cell name="doi">10.1787/rev_stats-2018-en</cell>
    <cell name="title">Revenue Statistics 2018 (en)</cell>
    <cell name="subtitle"/>
    <cell name="language">English</cell>
    <cell name="medium">PDF</cell>
    <cell name="availability">Forthcoming</cell>
    <cell name="date of publication">2018-11-29</cell>
    <cell name="embargo date">2018-11-29T10:00:00Z</cell>
    <cell name="launch date/time">2018-11-29T10:00:00Z</cell>
    <cell name="ilibrary last export date">2018-11-13T05:41:04.443Z</cell>
    <cell name="freepreview last export date"/>
    <cell name="catalogue type">Book</cell>
    <cell name="fti loaded?"/>
  </row>
  <row index="8">
    <cell name="directorate">Centre for Tax Policy and Administration</cell>
    <cell name="doi">10.1787/rev_stats-2018-en</cell>
    <cell name="title">Revenue Statistics 2018 (en)</cell>
    <cell name="subtitle"/>
    <cell name="language">English</cell>
    <cell name="medium">Paperback</cell>
    <cell name="availability">Not yet available</cell>
    <cell name="date of publication">2018-11-29</cell>
    <cell name="embargo date">2018-11-29T10:00:00Z</cell>
    <cell name="launch date/time">2018-11-29T10:00:00Z</cell>
    <cell name="ilibrary last export date"/>
    <cell name="freepreview last export date"/>
    <cell name="catalogue type">Book</cell>
    <cell name="fti loaded?"/>
  </row>
  <row index="9">
    <cell name="directorate">Development Centre, Centre for Tax Policy and Administration</cell>
    <cell name="doi">10.1787/9789264308091-en</cell>
    <cell name="title">Revenue Statistics in Asian and Pacific Economies (en)</cell>
    <cell name="subtitle"/>
    <cell name="language">English</cell>
    <cell name="medium">PDF</cell>
    <cell name="availability">Forthcoming</cell>
    <cell name="date of publication">2018-11-29</cell>
    <cell name="embargo date">2018-11-29T10:00:00Z</cell>
    <cell name="launch date/time">2018-11-29T10:00:00Z</cell>
    <cell name="ilibrary last export date">2018-10-26T04:50:08.947Z</cell>
    <cell name="freepreview last export date"/>
    <cell name="catalogue type">Stand-alone monograph</cell>
    <cell name="fti loaded?"/>
  </row>
  <row index="10">
    <cell name="directorate">Development Centre, Centre for Tax Policy and Administration</cell>
    <cell name="doi">10.1787/9789264308091-en</cell>
    <cell name="title">Revenue Statistics in Asian and Pacific Economies (en)</cell>
    <cell name="subtitle"/>
    <cell name="language">English</cell>
    <cell name="medium">ePub</cell>
    <cell name="availability">Forthcoming</cell>
    <cell name="date of publication">2018-11-29</cell>
    <cell name="embargo date">2018-11-29T10:00:00Z</cell>
    <cell name="launch date/time"/>
    <cell name="ilibrary last export date">2018-10-26T04:50:08.947Z</cell>
    <cell name="freepreview last export date"/>
    <cell name="catalogue type">Stand-alone monograph</cell>
    <cell name="fti loaded?"/>
  </row>
  <row index="11">
    <cell name="directorate">Development Centre, Centre for Tax Policy and Administration</cell>
    <cell name="doi">10.1787/9789264308091-en</cell>
    <cell name="title">Revenue Statistics in Asian and Pacific Economies (en)</cell>
    <cell name="subtitle"/>
    <cell name="language">English</cell>
    <cell name="medium">Paperback</cell>
    <cell name="availability">Forthcoming</cell>
    <cell name="date of publication">2018-11-29</cell>
    <cell name="embargo date">2018-11-29T10:00:00Z</cell>
    <cell name="launch date/time">2018-11-29T10:00:00Z</cell>
    <cell name="ilibrary last export date"/>
    <cell name="freepreview last export date"/>
    <cell name="catalogue type">Stand-alone monograph</cell>
    <cell name="fti loaded?"/>
  </row>
  <row index="12">
    <cell name="directorate">Development Centre, Centre for Tax Policy and Administration</cell>
    <cell name="doi">10.1787/9789264308091-en</cell>
    <cell name="title">Revenue Statistics in Asian and Pacific Economies (en)</cell>
    <cell name="subtitle"/>
    <cell name="language">English</cell>
    <cell name="medium">HTML</cell>
    <cell name="availability">Not yet available</cell>
    <cell name="date of publication">2018-11-29</cell>
    <cell name="embargo date">2018-11-29T10:00:00Z</cell>
    <cell name="launch date/time"/>
    <cell name="ilibrary last export date">2018-10-26T04:50:08.947Z</cell>
    <cell name="freepreview last export date"/>
    <cell name="catalogue type">Stand-alone monograph</cell>
    <cell name="fti loaded?"/>
  </row>
  <row index="13">
    <cell name="directorate">Centre for Tax Policy and Administration</cell>
    <cell name="doi">10.1787/rev_stats-2018-fr</cell>
    <cell name="title">Statistiques des recettes publiques 2018 (fr)</cell>
    <cell name="subtitle"/>
    <cell name="language">French</cell>
    <cell name="medium">Paperback</cell>
    <cell name="availability">Not yet available</cell>
    <cell name="date of publication">2018-11-29</cell>
    <cell name="embargo date">2018-11-29T10:00:00Z</cell>
    <cell name="launch date/time">2018-11-29T10:00:00Z</cell>
    <cell name="ilibrary last export date"/>
    <cell name="freepreview last export date"/>
    <cell name="catalogue type">Book</cell>
    <cell name="fti loaded?"/>
  </row>
  <row index="14">
    <cell name="directorate">Centre for Tax Policy and Administration</cell>
    <cell name="doi">10.1787/rev_stats-2018-fr</cell>
    <cell name="title">Statistiques des recettes publiques 2018 (fr)</cell>
    <cell name="subtitle"/>
    <cell name="language">French</cell>
    <cell name="medium">PDF</cell>
    <cell name="availability">Forthcoming</cell>
    <cell name="date of publication">2018-11-29</cell>
    <cell name="embargo date">2018-11-29T10:00:00Z</cell>
    <cell name="launch date/time">2018-11-29T10:00:00Z</cell>
    <cell name="ilibrary last export date">2018-11-13T05:41:04.443Z</cell>
    <cell name="freepreview last export date"/>
    <cell name="catalogue type">Book</cell>
    <cell name="fti loaded?"/>
  </row>
  <row index="15">
    <cell name="directorate">Directorate for Employment, Labour and Social Affairs</cell>
    <cell name="doi">10.1787/health_glance_eur-2018-en</cell>
    <cell name="title">Health at a Glance: Europe 2018 (en)</cell>
    <cell name="subtitle">State of Health in the EU Cycle (en)</cell>
    <cell name="language">English</cell>
    <cell name="medium">PDF</cell>
    <cell name="availability">Forthcoming</cell>
    <cell name="date of publication">2018-11-22</cell>
    <cell name="embargo date">2018-11-22T12:00:00Z</cell>
    <cell name="launch date/time">2018-11-22T12:00:00Z</cell>
    <cell name="ilibrary last export date">2018-11-14T05:31:08.533Z</cell>
    <cell name="freepreview last export date"/>
    <cell name="catalogue type">Book</cell>
    <cell name="fti loaded?">✓</cell>
  </row>
  <row index="16">
    <cell name="directorate">Directorate for Employment, Labour and Social Affairs</cell>
    <cell name="doi">10.1787/health_glance_eur-2018-en</cell>
    <cell name="title">Health at a Glance: Europe 2018 (en)</cell>
    <cell name="subtitle">State of Health in the EU Cycle (en)</cell>
    <cell name="language">English</cell>
    <cell name="medium">Paperback</cell>
    <cell name="availability">Forthcoming</cell>
    <cell name="date of publication">2018-11-22</cell>
    <cell name="embargo date">2018-11-22T12:00:00Z</cell>
    <cell name="launch date/time">2018-11-22T12:00:00Z</cell>
    <cell name="ilibrary last export date"/>
    <cell name="freepreview last export date"/>
    <cell name="catalogue type">Book</cell>
    <cell name="fti loaded?"/>
  </row>
  <row index="17">
    <cell name="directorate">Directorate for Employment, Labour and Social Affairs</cell>
    <cell name="doi">10.1787/health_glance_eur-2018-en</cell>
    <cell name="title">Health at a Glance: Europe 2018 (en)</cell>
    <cell name="subtitle">State of Health in the EU Cycle (en)</cell>
    <cell name="language">English</cell>
    <cell name="medium">ePub</cell>
    <cell name="availability">Not yet available</cell>
    <cell name="date of publication">2018-11-22</cell>
    <cell name="embargo date">2018-11-22T12:00:00Z</cell>
    <cell name="launch date/time">2018-11-22T12:00:00Z</cell>
    <cell name="ilibrary last export date">2018-11-14T05:31:08.533Z</cell>
    <cell name="freepreview last export date"/>
    <cell name="catalogue type">Book</cell>
    <cell name="fti loaded?">✓</cell>
  </row>
  <row index="18">
    <cell name="directorate">Economics Department</cell>
    <cell name="doi">10.1787/eco_surveys-esp-2018-en</cell>
    <cell name="title">OECD Economic Surveys: Spain 2018 (en)</cell>
    <cell name="subtitle"/>
    <cell name="language">English</cell>
    <cell name="medium">Paperback</cell>
    <cell name="availability">Not yet available</cell>
    <cell name="date of publication">2018-11-22</cell>
    <cell name="embargo date">2018-11-22T10:00:00Z</cell>
    <cell name="launch date/time">2018-11-22T10:00:00Z</cell>
    <cell name="ilibrary last export date"/>
    <cell name="freepreview last export date"/>
    <cell name="catalogue type">Economic survey</cell>
    <cell name="fti loaded?"/>
  </row>
  <row index="19">
    <cell name="directorate">Economics Department</cell>
    <cell name="doi">10.1787/eco_surveys-esp-2018-en</cell>
    <cell name="title">OECD Economic Surveys: Spain 2018 (en)</cell>
    <cell name="subtitle"/>
    <cell name="language">English</cell>
    <cell name="medium">PDF</cell>
    <cell name="availability">Forthcoming</cell>
    <cell name="date of publication">2018-11-22</cell>
    <cell name="embargo date">2018-11-22T10:00:00Z</cell>
    <cell name="launch date/time">2018-11-22T10:00:00Z</cell>
    <cell name="ilibrary last export date">2018-11-09T06:38:47.273Z</cell>
    <cell name="freepreview last export date"/>
    <cell name="catalogue type">Economic survey</cell>
    <cell name="fti loaded?"/>
  </row>
  <row index="20">
    <cell name="directorate">Directorate for Public Governance</cell>
    <cell name="doi">10.1787/9789264306905-es</cell>
    <cell name="title">Estudio de la OCDE sobre Integridad en el Estado de Nuevo León, México (es)</cell>
    <cell name="subtitle">Dando sostenibilidad a las reformas de integridad (es)</cell>
    <cell name="language">Spanish</cell>
    <cell name="medium">PDF</cell>
    <cell name="availability">Forthcoming</cell>
    <cell name="date of publication">2018-11-21</cell>
    <cell name="embargo date">2018-11-21T17:00:00Z</cell>
    <cell name="launch date/time">2018-11-21T17:00:00Z</cell>
    <cell name="ilibrary last export date">2018-11-13T05:41:04.443Z</cell>
    <cell name="freepreview last export date"/>
    <cell name="catalogue type">Book</cell>
    <cell name="fti loaded?"/>
  </row>
  <row index="21">
    <cell name="directorate">Directorate for Public Governance</cell>
    <cell name="doi">10.1787/9789264306905-es</cell>
    <cell name="title">Estudio de la OCDE sobre Integridad en el Estado de Nuevo León, México (es)</cell>
    <cell name="subtitle">Dando sostenibilidad a las reformas de integridad (es)</cell>
    <cell name="language">Spanish</cell>
    <cell name="medium">Paperback</cell>
    <cell name="availability">Forthcoming</cell>
    <cell name="date of publication">2018-11-21</cell>
    <cell name="embargo date">2018-11-21T17:00:00Z</cell>
    <cell name="launch date/time">2018-12-21T17:00:00Z</cell>
    <cell name="ilibrary last export date"/>
    <cell name="freepreview last export date"/>
    <cell name="catalogue type">Book</cell>
    <cell name="fti loaded?"/>
  </row>
  <row index="22">
    <cell name="directorate">Directorate for Public Governance</cell>
    <cell name="doi">10.1787/9789264284463-en</cell>
    <cell name="title">OECD Integrity Review of Nuevo León, Mexico (en)</cell>
    <cell name="subtitle">Sustaining Integrity Reforms (en)</cell>
    <cell name="language">English</cell>
    <cell name="medium">PDF</cell>
    <cell name="availability">Forthcoming</cell>
    <cell name="date of publication">2018-11-21</cell>
    <cell name="embargo date">2018-11-21T17:00:00Z</cell>
    <cell name="launch date/time">2018-11-21T17:00:00Z</cell>
    <cell name="ilibrary last export date">2018-11-13T05:41:04.443Z</cell>
    <cell name="freepreview last export date"/>
    <cell name="catalogue type">Book</cell>
    <cell name="fti loaded?"/>
  </row>
  <row index="23">
    <cell name="directorate">Directorate for Public Governance</cell>
    <cell name="doi">10.1787/9789264284463-en</cell>
    <cell name="title">OECD Integrity Review of Nuevo León, Mexico (en)</cell>
    <cell name="subtitle">Sustaining Integrity Reforms (en)</cell>
    <cell name="language">English</cell>
    <cell name="medium">Paperback</cell>
    <cell name="availability">Forthcoming</cell>
    <cell name="date of publication">2018-11-21</cell>
    <cell name="embargo date">2018-11-21T17:00:00Z</cell>
    <cell name="launch date/time">2018-11-21T17:00:00Z</cell>
    <cell name="ilibrary last export date"/>
    <cell name="freepreview last export date"/>
    <cell name="catalogue type">Book</cell>
    <cell name="fti loaded?"/>
  </row>
  <row index="24">
    <cell name="directorate">Economics Department</cell>
    <cell name="doi">10.1787/eco_outlook-v2018-2-en</cell>
    <cell name="title">OECD Economic Outlook, Volume 2018 Issue 2 (en)</cell>
    <cell name="subtitle">Preliminary version (en)</cell>
    <cell name="language">English</cell>
    <cell name="medium">PDF</cell>
    <cell name="availability">Forthcoming</cell>
    <cell name="date of publication">2018-11-21</cell>
    <cell name="embargo date">2018-11-21T10:00:00Z</cell>
    <cell name="launch date/time">2018-11-21T10:00:00Z</cell>
    <cell name="ilibrary last export date">2018-11-13T05:41:04.443Z</cell>
    <cell name="freepreview last export date"/>
    <cell name="catalogue type">Book</cell>
    <cell name="fti loaded?"/>
  </row>
  <row index="25">
    <cell name="directorate">Economics Department</cell>
    <cell name="doi">10.1787/eco_outlook-v2018-2-en</cell>
    <cell name="title">OECD Economic Outlook, Volume 2018 Issue 2 (en)</cell>
    <cell name="subtitle">Preliminary version (en)</cell>
    <cell name="language">English</cell>
    <cell name="medium">Paperback</cell>
    <cell name="availability">Not yet available</cell>
    <cell name="date of publication">2018-11-21</cell>
    <cell name="embargo date">2018-11-21T10:00:00Z</cell>
    <cell name="launch date/time">2018-11-21T10:00:00Z</cell>
    <cell name="ilibrary last export date"/>
    <cell name="freepreview last export date"/>
    <cell name="catalogue type">Book</cell>
    <cell name="fti loaded?"/>
  </row>
  <row index="26">
    <cell name="directorate">Economics Department</cell>
    <cell name="doi">10.1787/eco_outlook-v2018-2-de</cell>
    <cell name="title">OECD-Wirtschaftsausblick, Ausgabe 2018/2 (de)</cell>
    <cell name="subtitle">Vorläufige Ausgabe (de)</cell>
    <cell name="language">German</cell>
    <cell name="medium">PDF</cell>
    <cell name="availability">Forthcoming</cell>
    <cell name="date of publication">2018-11-21</cell>
    <cell name="embargo date">2018-11-21T10:00:00Z</cell>
    <cell name="launch date/time">2018-11-21T10:00:00Z</cell>
    <cell name="ilibrary last export date">2018-11-14T05:31:08.533Z</cell>
    <cell name="freepreview last export date"/>
    <cell name="catalogue type">Book</cell>
    <cell name="fti loaded?"/>
  </row>
  <row index="27">
    <cell name="directorate">Economics Department</cell>
    <cell name="doi">10.1787/eco_outlook-v2018-2-de</cell>
    <cell name="title">OECD-Wirtschaftsausblick, Ausgabe 2018/2 (de)</cell>
    <cell name="subtitle">Vorläufige Ausgabe (de)</cell>
    <cell name="language">German</cell>
    <cell name="medium">Paperback</cell>
    <cell name="availability">Not yet available</cell>
    <cell name="date of publication">2018-11-21</cell>
    <cell name="embargo date">2018-11-21T10:00:00Z</cell>
    <cell name="launch date/time">2018-11-21T10:00:00Z</cell>
    <cell name="ilibrary last export date"/>
    <cell name="freepreview last export date"/>
    <cell name="catalogue type">Book</cell>
    <cell name="fti loaded?"/>
  </row>
  <row index="28">
    <cell name="directorate">Economics Department</cell>
    <cell name="doi">10.1787/eco_outlook-v2018-2-fr</cell>
    <cell name="title">Perspectives économiques de l'OCDE, Volume 2018 Numéro 2 (fr)</cell>
    <cell name="subtitle">Version préliminaire (fr)</cell>
    <cell name="language">French</cell>
    <cell name="medium">Paperback</cell>
    <cell name="availability">Not yet available</cell>
    <cell name="date of publication">2018-11-21</cell>
    <cell name="embargo date">2018-11-21T10:00:00Z</cell>
    <cell name="launch date/time">2018-11-21T10:00:00Z</cell>
    <cell name="ilibrary last export date"/>
    <cell name="freepreview last export date"/>
    <cell name="catalogue type">Book</cell>
    <cell name="fti loaded?"/>
  </row>
  <row index="29">
    <cell name="directorate">Economics Department</cell>
    <cell name="doi">10.1787/eco_outlook-v2018-2-fr</cell>
    <cell name="title">Perspectives économiques de l'OCDE, Volume 2018 Numéro 2 (fr)</cell>
    <cell name="subtitle">Version préliminaire (fr)</cell>
    <cell name="language">French</cell>
    <cell name="medium">PDF</cell>
    <cell name="availability">Forthcoming</cell>
    <cell name="date of publication">2018-11-21</cell>
    <cell name="embargo date">2018-11-21T10:00:00Z</cell>
    <cell name="launch date/time">2018-11-21T10:00:00Z</cell>
    <cell name="ilibrary last export date">2018-11-13T05:41:04.443Z</cell>
    <cell name="freepreview last export date"/>
    <cell name="catalogue type">Book</cell>
    <cell name="fti loaded?"/>
  </row>
  <row index="30">
    <cell name="directorate">Directorate for Education and Skills</cell>
    <cell name="doi">10.1787/f5bd9e57-en</cell>
    <cell name="title">The science of teaching science (en)</cell>
    <cell name="subtitle">An exploration of science teaching practices in PISA 2015 (en)</cell>
    <cell name="language">English</cell>
    <cell name="medium">PDF</cell>
    <cell name="availability">Published</cell>
    <cell name="date of publication">2018-11-19</cell>
    <cell name="embargo date">2018-11-19T04:00:00Z</cell>
    <cell name="launch date/time"/>
    <cell name="ilibrary last export date">2018-11-14T05:31:10.4122717Z</cell>
    <cell name="freepreview last export date">2018-11-13T20:21:02Z</cell>
    <cell name="catalogue type">Working paper</cell>
    <cell name="fti loaded?">✓, ✓</cell>
  </row>
  <row index="31">
    <cell name="directorate">Economics Department</cell>
    <cell name="doi">10.1787/24ad924a-en</cell>
    <cell name="title">Regulatory framework for the loan-based crowdfunding platforms (en)</cell>
    <cell name="subtitle"/>
    <cell name="language">English</cell>
    <cell name="medium">PDF</cell>
    <cell name="availability">Published</cell>
    <cell name="date of publication">2018-11-16</cell>
    <cell name="embargo date">2018-11-16T01:00:00Z</cell>
    <cell name="launch date/time"/>
    <cell name="ilibrary last export date"/>
    <cell name="freepreview last export date">2018-11-14T20:09:17Z</cell>
    <cell name="catalogue type">Working paper</cell>
    <cell name="fti loaded?">✓, ✓</cell>
  </row>
  <row index="32">
    <cell name="directorate">Economics Department</cell>
    <cell name="doi">10.1787/74c044b1-en</cell>
    <cell name="title">To what extent do policies contribute to self-employment? (en)</cell>
    <cell name="subtitle"/>
    <cell name="language">English</cell>
    <cell name="medium">PDF</cell>
    <cell name="availability">Published</cell>
    <cell name="date of publication">2018-11-16</cell>
    <cell name="embargo date">2018-11-16T01:00:00Z</cell>
    <cell name="launch date/time"/>
    <cell name="ilibrary last export date"/>
    <cell name="freepreview last export date">2018-11-14T20:09:17Z</cell>
    <cell name="catalogue type">Working paper</cell>
    <cell name="fti loaded?">✓, ✓</cell>
  </row>
  <row index="33">
    <cell name="directorate">Directorate for Education and Skills</cell>
    <cell name="doi">10.1787/9550aa4e-en</cell>
    <cell name="title">Changing interests and sustained knowledge in the TALIS 2018 framework (en)</cell>
    <cell name="subtitle"/>
    <cell name="language">English</cell>
    <cell name="medium">PDF</cell>
    <cell name="availability">Published</cell>
    <cell name="date of publication">2018-11-15</cell>
    <cell name="embargo date">2018-11-15T10:00:00Z</cell>
    <cell name="launch date/time"/>
    <cell name="ilibrary last export date"/>
    <cell name="freepreview last export date">2018-11-14T20:09:17Z</cell>
    <cell name="catalogue type">Working paper</cell>
    <cell name="fti loaded?">✓</cell>
  </row>
  <row index="34">
    <cell name="directorate">Directorate for Education and Skills</cell>
    <cell name="doi">10.1787/799337c2-en</cell>
    <cell name="title">Teaching and Learning International Survey (TALIS) 2018 Conceptual Framework (en)</cell>
    <cell name="subtitle"/>
    <cell name="language">English</cell>
    <cell name="medium">PDF</cell>
    <cell name="availability">Published</cell>
    <cell name="date of publication">2018-11-15</cell>
    <cell name="embargo date">2018-11-15T10:00:00Z</cell>
    <cell name="launch date/time"/>
    <cell name="ilibrary last export date">2018-11-14T05:31:10.4122717Z</cell>
    <cell name="freepreview last export date">2018-11-13T20:21:02Z</cell>
    <cell name="catalogue type">Working paper</cell>
    <cell name="fti loaded?">✓, ✓</cell>
  </row>
  <row index="35">
    <cell name="directorate">International Energy Agency</cell>
    <cell name="doi">10.1787/weo-2018-12-en</cell>
    <cell name="title">Alternative electricity futures (en)</cell>
    <cell name="subtitle"/>
    <cell name="language">English</cell>
    <cell name="medium">PDF</cell>
    <cell name="availability">Published</cell>
    <cell name="date of publication">2018-11-13</cell>
    <cell name="embargo date">2018-11-13T12:00:00Z</cell>
    <cell name="launch date/time"/>
    <cell name="ilibrary last export date">2018-11-13T05:41:04.443Z</cell>
    <cell name="freepreview last export date"/>
    <cell name="catalogue type">Chapter</cell>
    <cell name="fti loaded?">✓, ✓</cell>
  </row>
  <row index="36">
    <cell name="directorate">International Energy Agency</cell>
    <cell name="doi">10.1787/weo-2018-17-en</cell>
    <cell name="title">Definitions (en)</cell>
    <cell name="subtitle"/>
    <cell name="language">English</cell>
    <cell name="medium">PDF</cell>
    <cell name="availability">Published</cell>
    <cell name="date of publication">2018-11-13</cell>
    <cell name="embargo date">2018-11-13T12:00:00Z</cell>
    <cell name="launch date/time"/>
    <cell name="ilibrary last export date">2018-11-13T05:41:04.443Z</cell>
    <cell name="freepreview last export date"/>
    <cell name="catalogue type">Chapter</cell>
    <cell name="fti loaded?">✓, ✓</cell>
  </row>
  <row index="37">
    <cell name="directorate">International Energy Agency</cell>
    <cell name="doi">10.1787/weo-2018-16-en</cell>
    <cell name="title">Design of the scenarios (en)</cell>
    <cell name="subtitle"/>
    <cell name="language">English</cell>
    <cell name="medium">PDF</cell>
    <cell name="availability">Published</cell>
    <cell name="date of publication">2018-11-13</cell>
    <cell name="embargo date">2018-11-13T12:00:00Z</cell>
    <cell name="launch date/time"/>
    <cell name="ilibrary last export date">2018-11-13T05:41:04.443Z</cell>
    <cell name="freepreview last export date"/>
    <cell name="catalogue type">Chapter</cell>
    <cell name="fti loaded?">✓, ✓</cell>
  </row>
  <row index="38">
    <cell name="directorate">International Energy Agency</cell>
    <cell name="doi">10.1787/weo-2018-10-en</cell>
    <cell name="title">Electricity today (en)</cell>
    <cell name="subtitle"/>
    <cell name="language">English</cell>
    <cell name="medium">PDF</cell>
    <cell name="availability">Published</cell>
    <cell name="date of publication">2018-11-13</cell>
    <cell name="embargo date">2018-11-13T12:00:00Z</cell>
    <cell name="launch date/time"/>
    <cell name="ilibrary last export date">2018-11-13T05:41:04.443Z</cell>
    <cell name="freepreview last export date"/>
    <cell name="catalogue type">Chapter</cell>
    <cell name="fti loaded?">✓, ✓</cell>
  </row>
  <row index="39">
    <cell name="directorate">International Energy Agency</cell>
    <cell name="doi">10.1787/weo-2018-5-en</cell>
    <cell name="title">Energy and the Sustainable Development Goals (en)</cell>
    <cell name="subtitle"/>
    <cell name="language">English</cell>
    <cell name="medium">PDF</cell>
    <cell name="availability">Published</cell>
    <cell name="date of publication">2018-11-13</cell>
    <cell name="embargo date">2018-11-13T12:00:00Z</cell>
    <cell name="launch date/time"/>
    <cell name="ilibrary last export date">2018-11-13T05:41:04.443Z</cell>
    <cell name="freepreview last export date"/>
    <cell name="catalogue type">Chapter</cell>
    <cell name="fti loaded?">✓, ✓</cell>
  </row>
  <row index="40">
    <cell name="directorate">International Energy Agency</cell>
    <cell name="doi">10.1787/weo-2018-9-en</cell>
    <cell name="title">Energy efficiency and renewable energy (en)</cell>
    <cell name="subtitle"/>
    <cell name="language">English</cell>
    <cell name="medium">PDF</cell>
    <cell name="availability">Published</cell>
    <cell name="date of publication">2018-11-13</cell>
    <cell name="embargo date">2018-11-13T12:00:00Z</cell>
    <cell name="launch date/time"/>
    <cell name="ilibrary last export date">2018-11-13T05:41:04.443Z</cell>
    <cell name="freepreview last export date"/>
    <cell name="catalogue type">Chapter</cell>
    <cell name="fti loaded?">✓, ✓</cell>
  </row>
  <row index="41">
    <cell name="directorate">International Energy Agency</cell>
    <cell name="doi">10.1787/weo-2018-2-en</cell>
    <cell name="title">Executive Summary (en)</cell>
    <cell name="subtitle"/>
    <cell name="language">English</cell>
    <cell name="medium">PDF</cell>
    <cell name="availability">Published</cell>
    <cell name="date of publication">2018-11-13</cell>
    <cell name="embargo date">2018-11-13T12:00:00Z</cell>
    <cell name="launch date/time"/>
    <cell name="ilibrary last export date">2018-11-13T05:41:04.443Z</cell>
    <cell name="freepreview last export date"/>
    <cell name="catalogue type">Chapter</cell>
    <cell name="fti loaded?">✓, ✓</cell>
  </row>
  <row index="42">
    <cell name="directorate">International Energy Agency</cell>
    <cell name="doi">10.1787/weo-2018-1-en</cell>
    <cell name="title">Foreword (en)</cell>
    <cell name="subtitle"/>
    <cell name="language">English</cell>
    <cell name="medium">PDF</cell>
    <cell name="availability">Published</cell>
    <cell name="date of publication">2018-11-13</cell>
    <cell name="embargo date">2018-11-13T12:00:00Z</cell>
    <cell name="launch date/time"/>
    <cell name="ilibrary last export date">2018-11-13T05:41:04.443Z</cell>
    <cell name="freepreview last export date"/>
    <cell name="catalogue type">Chapter</cell>
    <cell name="fti loaded?">✓, ✓</cell>
  </row>
  <row index="43">
    <cell name="directorate">International Energy Agency</cell>
    <cell name="doi">10.1787/weo-2018-13-en</cell>
    <cell name="title">Global implications of an electrifying future (en)</cell>
    <cell name="subtitle"/>
    <cell name="language">English</cell>
    <cell name="medium">PDF</cell>
    <cell name="availability">Published</cell>
    <cell name="date of publication">2018-11-13</cell>
    <cell name="embargo date">2018-11-13T12:00:00Z</cell>
    <cell name="launch date/time"/>
    <cell name="ilibrary last export date">2018-11-13T05:41:04.443Z</cell>
    <cell name="freepreview last export date"/>
    <cell name="catalogue type">Chapter</cell>
    <cell name="fti loaded?">✓, ✓</cell>
  </row>
  <row index="44">
    <cell name="directorate">International Energy Agency</cell>
    <cell name="doi">10.1787/weo-2018-14-en</cell>
    <cell name="title">Innovation and the environmentalperformance of oil and gas supply (en)</cell>
    <cell name="subtitle"/>
    <cell name="language">English</cell>
    <cell name="medium">PDF</cell>
    <cell name="availability">Published</cell>
    <cell name="date of publication">2018-11-13</cell>
    <cell name="embargo date">2018-11-13T12:00:00Z</cell>
    <cell name="launch date/time"/>
    <cell name="ilibrary last export date">2018-11-13T05:41:04.443Z</cell>
    <cell name="freepreview last export date"/>
    <cell name="catalogue type">Chapter</cell>
    <cell name="fti loaded?">✓, ✓</cell>
  </row>
  <row index="45">
    <cell name="directorate">International Energy Agency</cell>
    <cell name="doi">10.1787/weo-2018-3-en</cell>
    <cell name="title">Introduction (en)</cell>
    <cell name="subtitle"/>
    <cell name="language">English</cell>
    <cell name="medium">PDF</cell>
    <cell name="availability">Published</cell>
    <cell name="date of publication">2018-11-13</cell>
    <cell name="embargo date">2018-11-13T12:00:00Z</cell>
    <cell name="launch date/time"/>
    <cell name="ilibrary last export date">2018-11-13T05:41:04.443Z</cell>
    <cell name="freepreview last export date"/>
    <cell name="catalogue type">Chapter</cell>
    <cell name="fti loaded?">✓, ✓</cell>
  </row>
  <row index="46">
    <cell name="directorate">International Energy Agency</cell>
    <cell name="doi">10.1787/weo-2018-8-en</cell>
    <cell name="title">Outlook for coal (en)</cell>
    <cell name="subtitle"/>
    <cell name="language">English</cell>
    <cell name="medium">PDF</cell>
    <cell name="availability">Published</cell>
    <cell name="date of publication">2018-11-13</cell>
    <cell name="embargo date">2018-11-13T12:00:00Z</cell>
    <cell name="launch date/time"/>
    <cell name="ilibrary last export date">2018-11-13T05:41:04.443Z</cell>
    <cell name="freepreview last export date"/>
    <cell name="catalogue type">Chapter</cell>
    <cell name="fti loaded?">✓, ✓</cell>
  </row>
  <row index="47">
    <cell name="directorate">International Energy Agency</cell>
    <cell name="doi">10.1787/weo-2018-11-en</cell>
    <cell name="title">Outlook for electricity demand and supply (en)</cell>
    <cell name="subtitle"/>
    <cell name="language">English</cell>
    <cell name="medium">PDF</cell>
    <cell name="availability">Published</cell>
    <cell name="date of publication">2018-11-13</cell>
    <cell name="embargo date">2018-11-13T12:00:00Z</cell>
    <cell name="launch date/time"/>
    <cell name="ilibrary last export date">2018-11-14T05:31:08.533Z</cell>
    <cell name="freepreview last export date"/>
    <cell name="catalogue type">Chapter</cell>
    <cell name="fti loaded?">✓, ✓</cell>
  </row>
  <row index="48">
    <cell name="directorate">International Energy Agency</cell>
    <cell name="doi">10.1787/weo-2018-7-en</cell>
    <cell name="title">Outlook for natural gas (en)</cell>
    <cell name="subtitle"/>
    <cell name="language">English</cell>
    <cell name="medium">PDF</cell>
    <cell name="availability">Published</cell>
    <cell name="date of publication">2018-11-13</cell>
    <cell name="embargo date">2018-11-13T12:00:00Z</cell>
    <cell name="launch date/time"/>
    <cell name="ilibrary last export date">2018-11-13T05:41:04.443Z</cell>
    <cell name="freepreview last export date"/>
    <cell name="catalogue type">Chapter</cell>
    <cell name="fti loaded?">✓, ✓</cell>
  </row>
  <row index="49">
    <cell name="directorate">International Energy Agency</cell>
    <cell name="doi">10.1787/weo-2018-6-en</cell>
    <cell name="title">Outlook for oil (en)</cell>
    <cell name="subtitle"/>
    <cell name="language">English</cell>
    <cell name="medium">PDF</cell>
    <cell name="availability">Published</cell>
    <cell name="date of publication">2018-11-13</cell>
    <cell name="embargo date">2018-11-13T12:00:00Z</cell>
    <cell name="launch date/time"/>
    <cell name="ilibrary last export date">2018-11-13T05:41:04.443Z</cell>
    <cell name="freepreview last export date"/>
    <cell name="catalogue type">Chapter</cell>
    <cell name="fti loaded?">✓, ✓</cell>
  </row>
  <row index="50">
    <cell name="directorate">International Energy Agency</cell>
    <cell name="doi">10.1787/weo-2018-4-en</cell>
    <cell name="title">Overview and key findings (en)</cell>
    <cell name="subtitle"/>
    <cell name="language">English</cell>
    <cell name="medium">PDF</cell>
    <cell name="availability">Published</cell>
    <cell name="date of publication">2018-11-13</cell>
    <cell name="embargo date">2018-11-13T12:00:00Z</cell>
    <cell name="launch date/time"/>
    <cell name="ilibrary last export date">2018-11-13T05:41:04.443Z</cell>
    <cell name="freepreview last export date"/>
    <cell name="catalogue type">Chapter</cell>
    <cell name="fti loaded?">✓, ✓</cell>
  </row>
  <row index="51">
    <cell name="directorate">International Energy Agency</cell>
    <cell name="doi">10.1787/weo-2018-18-en</cell>
    <cell name="title">References (en)</cell>
    <cell name="subtitle"/>
    <cell name="language">English</cell>
    <cell name="medium">PDF</cell>
    <cell name="availability">Published</cell>
    <cell name="date of publication">2018-11-13</cell>
    <cell name="embargo date">2018-11-13T12:00:00Z</cell>
    <cell name="launch date/time"/>
    <cell name="ilibrary last export date">2018-11-13T05:41:04.443Z</cell>
    <cell name="freepreview last export date"/>
    <cell name="catalogue type">Chapter</cell>
    <cell name="fti loaded?">✓, ✓</cell>
  </row>
  <row index="52">
    <cell name="directorate">International Energy Agency</cell>
    <cell name="doi">10.1787/weo-2018-15-en</cell>
    <cell name="title">Tables for scenario projections (en)</cell>
    <cell name="subtitle"/>
    <cell name="language">English</cell>
    <cell name="medium">PDF</cell>
    <cell name="availability">Published</cell>
    <cell name="date of publication">2018-11-13</cell>
    <cell name="embargo date">2018-11-13T12:00:00Z</cell>
    <cell name="launch date/time"/>
    <cell name="ilibrary last export date">2018-11-13T05:41:04.443Z</cell>
    <cell name="freepreview last export date"/>
    <cell name="catalogue type">Chapter</cell>
    <cell name="fti loaded?">✓, ✓</cell>
  </row>
</report>
